ContainerDetails/__init__.py
ContainerDetails/expose.py
ContainerDetails/list_expose.py
olgamrl_Python_Gui_p2-1.0.data/scripts/expose.py
olgamrl_Python_Gui_p2-1.0.data/scripts/list_expose.py
olgamrl_Python_Gui_p2-1.0.dist-info/METADATA
olgamrl_Python_Gui_p2-1.0.dist-info/WHEEL
olgamrl_Python_Gui_p2-1.0.dist-info/top_level.txt
olgamrl_Python_Gui_p2-1.0.dist-info/RECORD
