Metadata-Version: 2.1
Name: olgamrl-Python-Gui-p2
Version: 1.0
Summary: A small gui example package
Home-page: https://pypi.org/manage/projects/
Author: Olga M
Author-email: olga.meltsin@example.com
License: UNKNOWN
Platform: UNKNOWN
Requires-Python: >=3.9
Requires-Dist: docker
Requires-Dist: flask
